[
	{
		"type":"lrpanel",
		"title":"about",
		"title_tw":"關於CFRLab",
		"pic":[
			"https://via.placeholder.com/350x350.png",
			"https://via.placeholder.com/350x350.png",
			"https://via.placeholder.com/350x350.png",
			"https://via.placeholder.com/350x350.png"
		],
		"content":
			"CFRLab, Computing Fabrication Research Labortory is a education platform, founded on the ideas that design form can serve algrothim, media, space, and activites inspiring surroundings and arising a positive effect on people’s lives."
	}
]